{
	"configurations" : 
	[
		{
			"directories" : 
			[
				{
					"build" : ".",
					"hasInstallRule" : true,
					"jsonFile" : "directory-.-16c9c25e8c203953fb2a.json",
					"minimumCMakeVersion" : 
					{
						"string" : "3.12"
					},
					"projectIndex" : 0,
					"source" : ".",
					"targetIndexes" : 
					[
						0,
						1
					]
				}
			],
			"name" : "",
			"projects" : 
			[
				{
					"directoryIndexes" : 
					[
						0
					],
					"name" : "nexon_base",
					"targetIndexes" : 
					[
						0,
						1
					]
				}
			],
			"targets" : 
			[
				{
					"directoryIndex" : 0,
					"id" : "nexon_base_uninstall::@6890427a1f51a3e7e1df",
					"jsonFile" : "target-nexon_base_uninstall-a94bebc03409515b6caf.json",
					"name" : "nexon_base_uninstall",
					"projectIndex" : 0
				},
				{
					"directoryIndex" : 0,
					"id" : "uninstall::@6890427a1f51a3e7e1df",
					"jsonFile" : "target-uninstall-fc6586ad35298e2df89d.json",
					"name" : "uninstall",
					"projectIndex" : 0
				}
			]
		}
	],
	"kind" : "codemodel",
	"paths" : 
	{
		"build" : "/home/bobby/nexon_ws/build/nexon_base",
		"source" : "/home/bobby/nexon_ws/src/nexon/nexon_base"
	},
	"version" : 
	{
		"major" : 2,
		"minor" : 3
	}
}
